CHANGELOG.md
lacecore/__init__.py
lacecore/_analysis/__init__.py
lacecore/_analysis/analysis_mixin.py
lacecore/_common/__init__.py
lacecore/_common/reindexing.py
lacecore/_common/tri.py
lacecore/_common/validation.py
lacecore/_group_map.py
lacecore/_mesh.py
lacecore/_obj/__init__.py
lacecore/_obj/loader.py
lacecore/_obj/writer.py
lacecore/_selection/__init__.py
lacecore/_selection/reconcile_selection.py
lacecore/_selection/selection_mixin.py
lacecore/_selection/selection_object.py
lacecore/_transform/__init__.py
lacecore/_transform/transform_mixin.py
lacecore/_transform/transform_object.py
lacecore/shapes/__init__.py
lacecore/shapes/_shapes.py
lacecore-2.4.3.dist-info/LICENSE
lacecore-2.4.3.dist-info/WHEEL
lacecore-2.4.3.dist-info/METADATA
lacecore-2.4.3.dist-info/RECORD
