Metadata-Version: 2.1
Name: lacecore
Version: 2.4.3
Summary: Polygonal meshes optimized for cloud computation
Home-page: https://github.com/lace/lacecore
License: BSD-2-Clause
Author: Paul Melnikow
Author-email: github@paulmelnikow.com
Requires-Python: >=3.7,<4
Classifier: Development Status :: 5 - Production/Stable
Classifier: Intended Audience :: Developers
Classifier: Intended Audience :: Manufacturing
Classifier: Intended Audience :: Science/Research
Classifier: License :: OSI Approved :: BSD License
Classifier: Operating System :: OS Independent
Classifier: Programming Language :: Python :: 3
Classifier: Programming Language :: Python :: 3.7
Classifier: Programming Language :: Python :: 3.8
Classifier: Programming Language :: Python :: 3.9
Classifier: Topic :: Artistic Software
Classifier: Topic :: Multimedia :: Graphics :: 3D Modeling
Classifier: Topic :: Scientific/Engineering :: Visualization
Provides-Extra: obj
Requires-Dist: numpy (<1.19.0)
Requires-Dist: ounce (>=1.1.0,<2.0)
Requires-Dist: polliwog (>=2.1.0,<3.0)
Requires-Dist: tinymetabobjloader (==2.0.0a0); extra == "obj"
Requires-Dist: vg (>=2.0.0)
Project-URL: Documentation, https://lacecore.readthedocs.io/en/stable/
Project-URL: Repository, https://github.com/lace/lacecore
